LICENSE
xrpl/__init__.py
xrpl/account/__init__.py
xrpl/account/main.py
xrpl/account/py.typed
xrpl/account/transaction_history.py
xrpl/asyncio/__init__.py
xrpl/asyncio/account/__init__.py
xrpl/asyncio/account/main.py
xrpl/asyncio/account/py.typed
xrpl/asyncio/account/transaction_history.py
xrpl/asyncio/clients/__init__.py
xrpl/asyncio/clients/async_client.py
xrpl/asyncio/clients/async_json_rpc_client.py
xrpl/asyncio/clients/async_websocket_client.py
xrpl/asyncio/clients/client.py
xrpl/asyncio/clients/exceptions.py
xrpl/asyncio/clients/json_rpc_base.py
xrpl/asyncio/clients/py.typed
xrpl/asyncio/clients/utils.py
xrpl/asyncio/clients/websocket_base.py
xrpl/asyncio/ledger/__init__.py
xrpl/asyncio/ledger/main.py
xrpl/asyncio/ledger/py.typed
xrpl/asyncio/ledger/utils.py
xrpl/asyncio/py.typed
xrpl/asyncio/transaction/__init__.py
xrpl/asyncio/transaction/main.py
xrpl/asyncio/transaction/py.typed
xrpl/asyncio/transaction/reliable_submission.py
xrpl/asyncio/wallet/__init__.py
xrpl/asyncio/wallet/py.typed
xrpl/asyncio/wallet/wallet_generation.py
xrpl/clients/__init__.py
xrpl/clients/json_rpc_client.py
xrpl/clients/py.typed
xrpl/clients/sync_client.py
xrpl/clients/websocket_client.py
xrpl/constants.py
xrpl/core/__init__.py
xrpl/core/addresscodec/__init__.py
xrpl/core/addresscodec/codec.py
xrpl/core/addresscodec/exceptions.py
xrpl/core/addresscodec/main.py
xrpl/core/addresscodec/py.typed
xrpl/core/addresscodec/utils.py
xrpl/core/binarycodec/__init__.py
xrpl/core/binarycodec/binary_wrappers/__init__.py
xrpl/core/binarycodec/binary_wrappers/binary_parser.py
xrpl/core/binarycodec/binary_wrappers/binary_serializer.py
xrpl/core/binarycodec/definitions/__init__.py
xrpl/core/binarycodec/definitions/definitions.json
xrpl/core/binarycodec/definitions/definitions.py
xrpl/core/binarycodec/definitions/field_header.py
xrpl/core/binarycodec/definitions/field_info.py
xrpl/core/binarycodec/definitions/field_instance.py
xrpl/core/binarycodec/exceptions.py
xrpl/core/binarycodec/field_id_codec.py
xrpl_py_cheng-4.4.90.dist-info/LICENSE
xrpl_py_cheng-4.4.90.dist-info/METADATA
xrpl_py_cheng-4.4.90.dist-info/WHEEL
xrpl_py_cheng-4.4.90.dist-info/RECORD
